{
  "metadata": {
    "timestamp": "2026-04-05T23:08:57.844017",
    "tokens_fetched": 29,
    "holders_fetched": 0,
    "whales_detected": 7,
    "agent": "collect_and_score_v1.0"
  },
  "raw_data": [
    {
      "symbol": "SWING",
      "name": "The Last Swing",
      "address": "2izfNJ5bACaQDKyqGUYicSKhFE963TnkBo9tWxiqpump",
      "chain": "SOL",
      "status": "active",
      "price_usd": 4.376e-06,
      "price_change_1h": 0.0,
      "price_change_6h": 0.74,
      "price_change_24h": -18.0,
      "volume_24h": 778.11,
      "volume_6h": 135.93,
      "volume_1h": 0.0,
      "volume_5m": 0.0,
      "liquidity_usd": 5840.64,
      "market_cap": 4376.0,
      "holder_count": 0,
      "holders_source": "rpc",
      "socials": {
        "twitter": "https://x.com/i/communities/2037838354025222210",
        "telegram": null,
        "website": null
      },
      "pair_created_at": 1774613471000,
      "age_hours": 226,
      "age_days": 9.4,
      "timestamp": "2026-04-05T23:05:35.920084",
      "source": "dexscreener",
      "vol_acceleration": 1.0,
      "vol_status": "NORMAL"
    },
    {
      "symbol": "Deadwhale",
      "name": "Deadwhale",
      "address": "91E4cACQcnWDf7wYmwwM81HjLvCe6FR6vDT518ospump",
      "chain": "SOL",
      "status": "active",
      "price_usd": 0.0001035,
      "price_change_1h": 0.22,
      "price_change_6h": -10.9,
      "price_change_24h": 5.39,
      "volume_24h": 48725.39,
      "volume_6h": 7368.22,
      "volume_1h": 1297.05,
      "volume_5m": 0.46,
      "liquidity_usd": 31882.71,
      "market_cap": 103533.0,
      "holder_count": 0,
      "holders_source": "rpc",
      "socials": {
        "twitter": "https://x.com/i/communities/2037268358526095583",
        "telegram": null,
        "website": "https://deadwhalememe.com/"
      },
      "pair_created_at": 1774560112000,
      "age_hours": 241,
      "age_days": 10.0,
      "timestamp": "2026-04-05T23:05:41.999752",
      "source": "dexscreener",
      "vol_acceleration": 1.0,
      "vol_status": "NORMAL"
    },
    {
      "symbol": "CAPYBARA",
      "name": "Mythos",
      "address": "Csdoc8vo3ryZ9tSiXxWYsZRTKCMmywG5pR8SC47Hab6B",
      "chain": "SOL",
      "status": "active",
      "price_usd": 1.635e-05,
      "price_change_1h": 1.97,
      "price_change_6h": 0.41,
      "price_change_24h": -6.07,
      "volume_24h": 5216.67,
      "volume_6h": 227.56,
      "volume_1h": 7.89,
      "volume_5m": 0.0,
      "liquidity_usd": 10975.13,
      "market_cap": 13979.0,
      "holder_count": 0,
      "holders_source": "rpc",
      "socials": {
        "twitter": "https://x.com/i/communities/2037453944201388141",
        "telegram": null,
        "website": null
      },
      "pair_created_at": 1774578902000,
      "age_hours": 236,
      "age_days": 9.8,
      "timestamp": "2026-04-05T23:05:48.078283",
      "source": "dexscreener",
      "vol_acceleration": 1.0,
      "vol_status": "NORMAL"
    },
    {
      "symbol": "VAULT",
      "name": "VaultBags",
      "address": "4iCRYJHvwUE21duaQ1nQcUXkh7wYNQai9aBihd3FBAGS",
      "chain": "SOL",
      "status": "active",
      "price_usd": 1.596e-05,
      "price_change_1h": -2.39,
      "price_change_6h": -7.39,
      "price_change_24h": -12.84,
      "volume_24h": 2059.28,
      "volume_6h": 732.22,
      "volume_1h": 35.66,
      "volume_5m": 0.0,
      "liquidity_usd": 8539.58,
      "market_cap": 15963.0,
      "holder_count": 0,
      "holders_source": "rpc",
      "socials": {
        "twitter": "https://x.com/VaultBags",
        "telegram": "https://t.me/VaultBags",
        "website": "https://vaultbags.app/"
      },
      "pair_created_at": 1774431452000,
      "age_hours": 277,
      "age_days": 11.5,
      "timestamp": "2026-04-05T23:06:00.276318",
      "source": "dexscreener",
      "vol_acceleration": 1.0,
      "vol_status": "NORMAL"
    },
    {
      "symbol": "dapang",
      "name": "D\u00e0 P\u00e0ng",
      "address": "CpP36fvZmbcDUH9tQihQZTcvH2ApwRzHh2pPojyWpump",
      "chain": "SOL",
      "status": "active",
      "price_usd": 7.563e-06,
      "price_change_1h": 0.0,
      "price_change_6h": 0.92,
      "price_change_24h": -6.35,
      "volume_24h": 257.44,
      "volume_6h": 2.15,
      "volume_1h": 0.0,
      "volume_5m": 0.0,
      "liquidity_usd": 8125.16,
      "market_cap": 7562.0,
      "holder_count": 0,
      "holders_source": "rpc",
      "socials": {
        "twitter": "https://x.com/MariusDima39211",
        "telegram": "https://t.me/DaPangOfficialCTO",
        "website": "https://dapangsolana.com/"
      },
      "pair_created_at": 1774293830000,
      "age_hours": 315,
      "age_days": 13.1,
      "timestamp": "2026-04-05T23:06:06.373739",
      "source": "dexscreener",
      "vol_acceleration": 1.0,
      "vol_status": "NORMAL"
    },
    {
      "symbol": "PUNCH",
      "name": "\u30d1\u30f3\u30c1",
      "address": "NV2RYH954cTJ3ckFUpvfqaQXU4ARqqDH3562nFSpump",
      "chain": "SOL",
      "status": "active",
      "price_usd": 0.01188,
      "price_change_1h": -0.8,
      "price_change_6h": -4.59,
      "price_change_24h": -9.55,
      "volume_24h": 696374.33,
      "volume_6h": 129416.76,
      "volume_1h": 20204.96,
      "volume_5m": 634.15,
      "liquidity_usd": 673474.15,
      "market_cap": 11880216.0,
      "holder_count": 0,
      "holders_source": "rpc",
      "socials": {
        "twitter": "https://x.com/punch_ganbare?s=21&t=ruzx1xkKsZ3vDPRkeDVwPg",
        "telegram": "https://t.me/punchverif",
        "website": "http://www.punchonsolana.live/"
      },
      "pair_created_at": 1770282065000,
      "age_hours": 1430,
      "age_days": 59.6,
      "timestamp": "2026-04-05T23:06:12.447339",
      "source": "dexscreener",
      "vol_acceleration": 1.0,
      "vol_status": "NORMAL"
    },
    {
      "symbol": "Jellybean",
      "name": "Jellybean",
      "address": "412zDygnwP9DzitnQVgRKUFFTDmrYScFch6P2k39pump",
      "chain": "SOL",
      "status": "active",
      "price_usd": 0.0001299,
      "price_change_1h": 0.47,
      "price_change_6h": 0.43,
      "price_change_24h": -19.03,
      "volume_24h": 37235.6,
      "volume_6h": 6164.07,
      "volume_1h": 102.98,
      "volume_5m": 0.0,
      "liquidity_usd": 51496.92,
      "market_cap": 129432.0,
      "holder_count": 0,
      "holders_source": "rpc",
      "socials": {
        "twitter": "https://x.com/jellybeanonsol?s=21",
        "telegram": null,
        "website": "https://thejellybean.fun"
      },
      "pair_created_at": 1770832014000,
      "age_hours": 1277,
      "age_days": 53.2,
      "timestamp": "2026-04-05T23:06:18.521944",
      "source": "dexscreener",
      "vol_acceleration": 1.0,
      "vol_status": "NORMAL"
    },
    {
      "symbol": "HODL",
      "name": "HODL",
      "address": "Hh3oTaqDCKKfdBgsQEvxp9sUwyNf8x9qmKqEMLBWpump",
      "chain": "SOL",
      "status": "active",
      "price_usd": 0.002679,
      "price_change_1h": -1.22,
      "price_change_6h": -2.27,
      "price_change_24h": -11.07,
      "volume_24h": 84547.11,
      "volume_6h": 30997.53,
      "volume_1h": 8224.91,
      "volume_5m": 0.19,
      "liquidity_usd": 206045.96,
      "market_cap": 2679822.0,
      "holder_count": 0,
      "holders_source": "rpc",
      "socials": {
        "twitter": "https://x.com/hodl2013",
        "telegram": "http://t.me/hodl_2013",
        "website": "https://hodl2013.com"
      },
      "pair_created_at": 1770925712000,
      "age_hours": 1251,
      "age_days": 52.1,
      "timestamp": "2026-04-05T23:06:24.639753",
      "source": "dexscreener",
      "vol_acceleration": 1.0,
      "vol_status": "NORMAL"
    },
    {
      "symbol": "JUICE",
      "name": "JUICE",
      "address": "2LzLh5pHg3nDQz6goTLAvDXfDbSBgAR8qem3bdXdpump",
      "chain": "SOL",
      "status": "active",
      "price_usd": 0.0004634,
      "price_change_1h": -1.42,
      "price_change_6h": -5.64,
      "price_change_24h": -10.25,
      "volume_24h": 9425.94,
      "volume_6h": 3923.0,
      "volume_1h": 276.74,
      "volume_5m": 14.25,
      "liquidity_usd": 75241.61,
      "market_cap": 443467.0,
      "holder_count": 0,
      "holders_source": "rpc",
      "socials": {
        "twitter": "https://x.com/JuiceLaunch",
        "telegram": null,
        "website": "https://www.juiceeverything.com/"
      },
      "pair_created_at": 1766441506000,
      "age_hours": 2496,
      "age_days": 104.0,
      "timestamp": "2026-04-05T23:06:30.731609",
      "source": "dexscreener",
      "vol_acceleration": 1.0,
      "vol_status": "NORMAL"
    },
    {
      "symbol": "PIZZA",
      "name": "Bitcoin Pizza",
      "address": "G9ivB7K41a4G8m1k4QdxxN4L5eGKL7Mr12S26B85pump",
      "chain": "SOL",
      "status": "active",
      "price_usd": 0.0001112,
      "price_change_1h": 1.37,
      "price_change_6h": -1.85,
      "price_change_24h": -1.48,
      "volume_24h": 10293.74,
      "volume_6h": 5092.29,
      "volume_1h": 148.09,
      "volume_5m": 0.0,
      "liquidity_usd": 35832.44,
      "market_cap": 111204.0,
      "holder_count": 0,
      "holders_source": "rpc",
      "socials": {
        "twitter": "https://x.com/i/communities/2028693567879729365",
        "telegram": null,
        "website": "https://btcpizza2010.com"
      },
      "pair_created_at": 1772520410000,
      "age_hours": 808,
      "age_days": 33.7,
      "timestamp": "2026-04-05T23:06:36.811164",
      "source": "dexscreener",
      "vol_acceleration": 1.0,
      "vol_status": "NORMAL"
    },
    {
      "symbol": "Momo-chan",
      "name": "\u30e2\u30e2\u3061\u3083\u3093",
      "address": "3zomtMhRRsBpLZeJLS86fgueXE7xAhoN8dnymNh8pump",
      "chain": "SOL",
      "status": "active",
      "price_usd": 4.681e-05,
      "price_change_1h": 2.71,
      "price_change_6h": 5.61,
      "price_change_24h": 8.1,
      "volume_24h": 10593.52,
      "volume_6h": 610.6,
      "volume_1h": 164.1,
      "volume_5m": 0.0,
      "liquidity_usd": 21924.73,
      "market_cap": 46800.0,
      "holder_count": 0,
      "holders_source": "rpc",
      "socials": {
        "twitter": "https://x.com/i/communities/2033773408174150024",
        "telegram": null,
        "website": "https://momochanonsol.com/"
      },
      "pair_created_at": 1773667317000,
      "age_hours": 489,
      "age_days": 20.4,
      "timestamp": "2026-04-05T23:06:42.905439",
      "source": "dexscreener",
      "vol_acceleration": 1.0,
      "vol_status": "NORMAL"
    },
    {
      "symbol": "MAX",
      "name": "maxxing",
      "address": "32CdQdBUxbCsLy5AUHWmyidfwhgGUr9N573NBUrDpump",
      "chain": "SOL",
      "status": "active",
      "price_usd": 0.002274,
      "price_change_1h": 2.26,
      "price_change_6h": 11.8,
      "price_change_24h": -8.59,
      "volume_24h": 166239.35,
      "volume_6h": 30096.91,
      "volume_1h": 8477.83,
      "volume_5m": 419.8,
      "liquidity_usd": 201943.82,
      "market_cap": 2273925.0,
      "holder_count": 0,
      "holders_source": "rpc",
      "socials": {
        "twitter": "https://x.com/_maxxing",
        "telegram": "https://t.me/maxxingTG",
        "website": "https://www.solmaxxing.xyz"
      },
      "pair_created_at": 1764628666000,
      "age_hours": 3000,
      "age_days": 125.0,
      "timestamp": "2026-04-05T23:06:48.982731",
      "source": "dexscreener",
      "vol_acceleration": 1.0,
      "vol_status": "NORMAL"
    },
    {
      "symbol": "testicle",
      "name": "testicle",
      "address": "4TyZGqRLG3VcHTGMcLBoPUmqYitMVojXinAmkL8xpump",
      "chain": "SOL",
      "status": "active",
      "price_usd": 0.007979,
      "price_change_1h": 2.83,
      "price_change_6h": 0.48,
      "price_change_24h": 5.0,
      "volume_24h": 457318.46,
      "volume_6h": 76614.72,
      "volume_1h": 25328.28,
      "volume_5m": 703.07,
      "liquidity_usd": 547180.1,
      "market_cap": 7979249.0,
      "holder_count": 0,
      "holders_source": "rpc",
      "socials": {
        "twitter": "https://x.com/testicletoken",
        "telegram": null,
        "website": "https://www.testicle.site/#about"
      },
      "pair_created_at": 1766317978000,
      "age_hours": 2531,
      "age_days": 105.5,
      "timestamp": "2026-04-05T23:06:55.036159",
      "source": "dexscreener",
      "vol_acceleration": 1.0,
      "vol_status": "NORMAL"
    },
    {
      "symbol": "NOTHING",
      "name": "You'll own nothing & be happy",
      "address": "F7pB3ZdfBnyFw2LRHydWEn9BmhEa5XihXLjhySFRpump",
      "chain": "SOL",
      "status": "active",
      "price_usd": 0.0004568,
      "price_change_1h": -0.33,
      "price_change_6h": -3.93,
      "price_change_24h": -3.95,
      "volume_24h": 11850.48,
      "volume_6h": 2214.47,
      "volume_1h": 62.44,
      "volume_5m": 0.0,
      "liquidity_usd": 100333.33,
      "market_cap": 456853.0,
      "holder_count": 0,
      "holders_source": "rpc",
      "socials": {
        "twitter": "https://x.com/youllownnothing",
        "telegram": "https://t.me/nothingmemechannel",
        "website": "https://www.ownnothing.xyz/"
      },
      "pair_created_at": 1762893903000,
      "age_hours": 3482,
      "age_days": 145.1,
      "timestamp": "2026-04-05T23:07:01.115180",
      "source": "dexscreener",
      "vol_acceleration": 1.0,
      "vol_status": "NORMAL"
    },
    {
      "symbol": "Artemis II",
      "name": "Artemis Moon Mission",
      "address": "EJzqpRPxgZZVoVVuCXuQBNXp7mQzeH6FENMfuLRbpump",
      "chain": "SOL",
      "status": "active",
      "price_usd": 5.151e-06,
      "price_change_1h": 10.71,
      "price_change_6h": 10.24,
      "price_change_24h": -7.87,
      "volume_24h": 942.92,
      "volume_6h": 462.8,
      "volume_1h": 128.15,
      "volume_5m": 0.0,
      "liquidity_usd": 6193.49,
      "market_cap": 5147.0,
      "holder_count": 0,
      "holders_source": "rpc",
      "socials": {
        "twitter": "https://x.com/Artemis2coin_",
        "telegram": "https://t.me/artemis2mission",
        "website": "https://www.artemis2coin.fun/"
      },
      "pair_created_at": 1769348704000,
      "age_hours": 1689,
      "age_days": 70.4,
      "timestamp": "2026-04-05T23:07:07.223360",
      "source": "dexscreener",
      "vol_acceleration": 1.0,
      "vol_status": "NORMAL"
    },
    {
      "symbol": "Buttcoin",
      "name": "Buttcoin",
      "address": "Cm6fNnMk7NfzStP9CZpsQA2v3jjzbcYGAxdJySmHpump",
      "chain": "SOL",
      "status": "active",
      "price_usd": 0.009141,
      "price_change_1h": -2.98,
      "price_change_6h": -1.56,
      "price_change_24h": -3.51,
      "volume_24h": 414535.51,
      "volume_6h": 122962.1,
      "volume_1h": 31535.09,
      "volume_5m": 1632.28,
      "liquidity_usd": 494423.68,
      "market_cap": 9141586.0,
      "holder_count": 0,
      "holders_source": "rpc",
      "socials": {
        "twitter": "https://x.com/buttcoin",
        "telegram": "https://t.me/buttcoinonpf",
        "website": "https://www.buttcoinfoundation.org/"
      },
      "pair_created_at": 1767965767000,
      "age_hours": 2073,
      "age_days": 86.4,
      "timestamp": "2026-04-05T23:07:13.275932",
      "source": "dexscreener",
      "vol_acceleration": 1.0,
      "vol_status": "NORMAL"
    },
    {
      "symbol": "Optimistic",
      "name": "Optimistic Minion",
      "address": "2pjcq9k2X5oSArNKiVeQ2ENB63eJt8pwCabciGQGpump",
      "chain": "SOL",
      "status": "active",
      "price_usd": 6.05e-05,
      "price_change_1h": -1.01,
      "price_change_6h": -16.08,
      "price_change_24h": -3.71,
      "volume_24h": 32076.37,
      "volume_6h": 5554.25,
      "volume_1h": 70.99,
      "volume_5m": 65.1,
      "liquidity_usd": 26654.51,
      "market_cap": 60506.0,
      "holder_count": 0,
      "holders_source": "rpc",
      "socials": {
        "twitter": "https://x.com/i/communities/2034488672767086881",
        "telegram": null,
        "website": "https://www.optimisticonsol.com/"
      },
      "pair_created_at": 1773896929000,
      "age_hours": 425,
      "age_days": 17.7,
      "timestamp": "2026-04-05T23:07:19.356077",
      "source": "dexscreener",
      "vol_acceleration": 1.0,
      "vol_status": "NORMAL"
    },
    {
      "symbol": "TripleT",
      "name": "Tung Tung Tung Sahur",
      "address": "J8PSdNP3QewKq2Z1JJJFDMaqF7KcaiJhR7gbr5KZpump",
      "chain": "SOL",
      "status": "active",
      "price_usd": 0.002734,
      "price_change_1h": 11.09,
      "price_change_6h": 23.21,
      "price_change_24h": 61.75,
      "volume_24h": 647301.3,
      "volume_6h": 262806.44,
      "volume_1h": 37699.89,
      "volume_5m": 396.97,
      "liquidity_usd": 197628.99,
      "market_cap": 2734417.0,
      "holder_count": 0,
      "holders_source": "rpc",
      "socials": {
        "twitter": "https://x.com/TripleTsol",
        "telegram": "https://t.me/TripleTCommunity",
        "website": "https://triplet.site/"
      },
      "pair_created_at": 1771922626000,
      "age_hours": 974,
      "age_days": 40.6,
      "timestamp": "2026-04-05T23:07:25.410939",
      "source": "dexscreener",
      "vol_acceleration": 1.0,
      "vol_status": "NORMAL"
    },
    {
      "symbol": "Rosie",
      "name": "Rosie",
      "address": "9QSjVAg5rDfBZPhvKwZcB63St3r6bqohP3Adurkjpump",
      "chain": "SOL",
      "status": "active",
      "price_usd": 0.000259,
      "price_change_1h": -3.59,
      "price_change_6h": -2.84,
      "price_change_24h": -12.33,
      "volume_24h": 55679.62,
      "volume_6h": 11067.87,
      "volume_1h": 1169.81,
      "volume_5m": 845.54,
      "liquidity_usd": 59362.4,
      "market_cap": 259061.0,
      "holder_count": 0,
      "holders_source": "rpc",
      "socials": {
        "twitter": "https://x.com/i/communities/2032561757802344845",
        "telegram": null,
        "website": "https://rosie-dog.vercel.app/"
      },
      "pair_created_at": 1773494598000,
      "age_hours": 537,
      "age_days": 22.4,
      "timestamp": "2026-04-05T23:07:31.464776",
      "source": "dexscreener",
      "vol_acceleration": 1.0,
      "vol_status": "NORMAL"
    },
    {
      "symbol": "Lobstar",
      "name": "Lobstar",
      "address": "AVF9F4C4j8b1Kh4BmNHqybDaHgnZpJ7W7yLvL7hUpump",
      "chain": "SOL",
      "status": "active",
      "price_usd": 0.004016,
      "price_change_1h": 0.94,
      "price_change_6h": -5.54,
      "price_change_24h": 0.07,
      "volume_24h": 179574.22,
      "volume_6h": 40757.87,
      "volume_1h": 4505.16,
      "volume_5m": 45.7,
      "liquidity_usd": 344546.25,
      "market_cap": 4016359.0,
      "holder_count": 0,
      "holders_source": "rpc",
      "socials": {
        "twitter": "https://x.com/i/communities/2024708338324299795",
        "telegram": null,
        "website": null
      },
      "pair_created_at": 1771561393000,
      "age_hours": 1074,
      "age_days": 44.8,
      "timestamp": "2026-04-05T23:07:37.539204",
      "source": "dexscreener",
      "vol_acceleration": 1.0,
      "vol_status": "NORMAL"
    },
    {
      "symbol": "snowball",
      "name": "snowball",
      "address": "Gbu7JAKhTVtGyRryg8cYPiKNhonXpUqbrZuCDjfUpump",
      "chain": "SOL",
      "status": "active",
      "price_usd": 0.0002175,
      "price_change_1h": 1.87,
      "price_change_6h": 1.34,
      "price_change_24h": -0.96,
      "volume_24h": 10884.72,
      "volume_6h": 1735.04,
      "volume_1h": 1345.3,
      "volume_5m": 30.37,
      "liquidity_usd": 82850.94,
      "market_cap": 207433.0,
      "holder_count": 0,
      "holders_source": "rpc",
      "socials": {
        "twitter": "https://x.com/i/communities/2001678386968564186",
        "telegram": "http://t.me/snowballctoportal",
        "website": "https://sb.fun"
      },
      "pair_created_at": 1766080714000,
      "age_hours": 2597,
      "age_days": 108.2,
      "timestamp": "2026-04-05T23:07:43.592985",
      "source": "dexscreener",
      "vol_acceleration": 1.0,
      "vol_status": "NORMAL"
    },
    {
      "symbol": "VIBECOIN",
      "name": "Vibing Cat Coin",
      "address": "AZbem4s8iLJE5eniDZJ7c8q1ahbfMwWgCA8TxVW2tDUB",
      "chain": "SOL",
      "status": "active",
      "price_usd": 0.002177,
      "price_change_1h": 0.0,
      "price_change_6h": 5.87,
      "price_change_24h": 0.02,
      "volume_24h": 11542.48,
      "volume_6h": 6843.62,
      "volume_1h": 0.0,
      "volume_5m": 0.0,
      "liquidity_usd": 113984.07,
      "market_cap": 2176718.0,
      "holder_count": 0,
      "holders_source": "rpc",
      "socials": {
        "twitter": "https://x.com/vibecoinonanon?s=21",
        "telegram": "https://t.me/VIBECOINCAT",
        "website": "https://anoncoin.it/vibecoin"
      },
      "pair_created_at": 1755441758000,
      "age_hours": 5552,
      "age_days": 231.3,
      "timestamp": "2026-04-05T23:07:49.685124",
      "source": "dexscreener",
      "vol_acceleration": 1.0,
      "vol_status": "NORMAL"
    },
    {
      "symbol": "GOYIM",
      "name": "Goyim",
      "address": "9S8edqWxoWz5LYLnxWUmWBJnePg35WfdYQp7HQkUpump",
      "chain": "SOL",
      "status": "active",
      "price_usd": 0.0003485,
      "price_change_1h": -15.24,
      "price_change_6h": -16.72,
      "price_change_24h": -31.95,
      "volume_24h": 55795.43,
      "volume_6h": 24398.75,
      "volume_1h": 19144.3,
      "volume_5m": 4237.85,
      "liquidity_usd": 91119.75,
      "market_cap": 348557.0,
      "holder_count": 0,
      "holders_source": "rpc",
      "socials": {
        "twitter": "https://x.com/goyimcoinsol",
        "telegram": null,
        "website": "https://goyim.network/"
      },
      "pair_created_at": 1769958443000,
      "age_hours": 1520,
      "age_days": 63.3,
      "timestamp": "2026-04-05T23:07:55.765840",
      "source": "dexscreener",
      "vol_acceleration": 1.0,
      "vol_status": "NORMAL"
    },
    {
      "symbol": "CHIBI",
      "name": "Chibification",
      "address": "2TpMjYXnrgxoeVCq2i6EAR8vNWqe5MNvHCz3bENNpump",
      "chain": "SOL",
      "status": "active",
      "price_usd": 0.0003795,
      "price_change_1h": 5.17,
      "price_change_6h": 10.92,
      "price_change_24h": 30.4,
      "volume_24h": 146476.43,
      "volume_6h": 52536.17,
      "volume_1h": 3958.61,
      "volume_5m": 1.9,
      "liquidity_usd": 70314.93,
      "market_cap": 379503.0,
      "holder_count": 0,
      "holders_source": "rpc",
      "socials": {
        "twitter": "https://x.com/i/communities/2037219921852010840",
        "telegram": "https://t.me/chibifanpage2",
        "website": null
      },
      "pair_created_at": 1773913358000,
      "age_hours": 421,
      "age_days": 17.5,
      "timestamp": "2026-04-05T23:08:01.854063",
      "source": "dexscreener",
      "vol_acceleration": 1.0,
      "vol_status": "NORMAL"
    },
    {
      "symbol": "NOTHING2",
      "name": "Nothing To Lose",
      "address": "7mtXLUoAcT9Sxrf1K5PjSmfkPbYMyMP5pmrdFFixbonk",
      "chain": "SOL",
      "status": "active",
      "price_usd": 8.931e-05,
      "price_change_1h": 0.63,
      "price_change_6h": -0.51,
      "price_change_24h": -6.46,
      "volume_24h": 2043.14,
      "volume_6h": 164.82,
      "volume_1h": 6.81,
      "volume_5m": 0.0,
      "liquidity_usd": 90161.55,
      "market_cap": 89319.0,
      "holder_count": 0,
      "holders_source": "rpc",
      "socials": {
        "twitter": "https://x.com/i/communities/2037084621385425092",
        "telegram": "https://t.me/nothing2losesol",
        "website": "https://nothingtolose.lol/"
      },
      "pair_created_at": 1774037046000,
      "age_hours": 387,
      "age_days": 16.1,
      "timestamp": "2026-04-05T23:08:07.906044",
      "source": "dexscreener",
      "vol_acceleration": 1.0,
      "vol_status": "NORMAL"
    },
    {
      "symbol": "Lockdown",
      "name": "Energy Lockdown",
      "address": "57wDExcxN6hAtYgcXoAXqSxrdCMwY4HNioWNM1Mtpump",
      "chain": "SOL",
      "status": "active",
      "price_usd": 3.293e-05,
      "price_change_1h": 3.63,
      "price_change_6h": 1.84,
      "price_change_24h": 37.7,
      "volume_24h": 6336.21,
      "volume_6h": 217.34,
      "volume_1h": 99.65,
      "volume_5m": 0.0,
      "liquidity_usd": 14963.6,
      "market_cap": 32797.0,
      "holder_count": 0,
      "holders_source": "rpc",
      "socials": {
        "twitter": "https://x.com/i/communities/2035616033952731544",
        "telegram": null,
        "website": "https://www.x.com/search?q=energy%20lockdown&src=typed_query"
      },
      "pair_created_at": 1774165370000,
      "age_hours": 351,
      "age_days": 14.6,
      "timestamp": "2026-04-05T23:08:14.000348",
      "source": "dexscreener",
      "vol_acceleration": 1.0,
      "vol_status": "NORMAL"
    },
    {
      "symbol": "TERAFAB",
      "name": "Terafab",
      "address": "EncFm8nRh1VBwcRmGugTUzoGsC1n2srWesKDkiMAYWLt",
      "chain": "SOL",
      "status": "active",
      "price_usd": 0.0001035,
      "price_change_1h": 4.29,
      "price_change_6h": -10.89,
      "price_change_24h": -29.76,
      "volume_24h": 55037.23,
      "volume_6h": 17587.51,
      "volume_1h": 3104.86,
      "volume_5m": 0.95,
      "liquidity_usd": 34853.3,
      "market_cap": 103533.0,
      "holder_count": 0,
      "holders_source": "rpc",
      "socials": {
        "twitter": "https://x.com/i/communities/2032819528636272922",
        "telegram": null,
        "website": "https://terafab.ceo/"
      },
      "pair_created_at": 1773495773000,
      "age_hours": 537,
      "age_days": 22.4,
      "timestamp": "2026-04-05T23:08:20.055848",
      "source": "dexscreener",
      "vol_acceleration": 1.0,
      "vol_status": "NORMAL"
    },
    {
      "symbol": "Lost",
      "name": "Pumpfun ruined my life",
      "address": "n3ShrNZRCoMrw5Gww7rPMxVbDq3to3YwsGkDz19pump",
      "chain": "SOL",
      "status": "active",
      "price_usd": 8.153e-05,
      "price_change_1h": -0.65,
      "price_change_6h": -19.5,
      "price_change_24h": -39.63,
      "volume_24h": 67634.11,
      "volume_6h": 14643.28,
      "volume_1h": 1425.8,
      "volume_5m": 7.22,
      "liquidity_usd": 27609.91,
      "market_cap": 81528.0,
      "holder_count": 0,
      "holders_source": "rpc",
      "socials": {
        "twitter": "https://x.com/lostcoinpump?s=21",
        "telegram": "https://t.me/lostcoincto",
        "website": "https://lostonpump.fun/"
      },
      "pair_created_at": 1774199898000,
      "age_hours": 341,
      "age_days": 14.2,
      "timestamp": "2026-04-05T23:08:32.195387",
      "source": "dexscreener",
      "vol_acceleration": 1.0,
      "vol_status": "NORMAL"
    },
    {
      "symbol": "7",
      "name": "The 7 Wanderers",
      "address": "84cAEWqiDsV5xXh6CB69Hi3HcnumBbdjH4THfyorpump",
      "chain": "SOL",
      "status": "active",
      "price_usd": 3.281e-05,
      "price_change_1h": -1.64,
      "price_change_6h": 2.51,
      "price_change_24h": -9.25,
      "volume_24h": 5463.36,
      "volume_6h": 1206.27,
      "volume_1h": 32.49,
      "volume_5m": 0.0,
      "liquidity_usd": 19466.3,
      "market_cap": 32814.0,
      "holder_count": 0,
      "holders_source": "rpc",
      "socials": {
        "twitter": "https://x.com/i/communities/2036098188285763894",
        "telegram": null,
        "website": "https://the7wanderers.com/"
      },
      "pair_created_at": 1774277677000,
      "age_hours": 320,
      "age_days": 13.3,
      "timestamp": "2026-04-05T23:08:38.249074",
      "source": "dexscreener",
      "vol_acceleration": 1.0,
      "vol_status": "NORMAL"
    }
  ]
}