{
  "metadata": {
    "timestamp": "2026-06-17T16:15:34.261189",
    "tokens_fetched": 28,
    "holders_fetched": 2,
    "whales_detected": 8,
    "agent": "collect_and_score_v1.0"
  },
  "raw_data": [
    {
      "symbol": "SWING",
      "name": "The Last Swing",
      "address": "2izfNJ5bACaQDKyqGUYicSKhFE963TnkBo9tWxiqpump",
      "chain": "SOL",
      "status": "active",
      "price_usd": 2.563e-06,
      "price_change_1h": 0.0,
      "price_change_6h": 0.0,
      "price_change_24h": 0.0,
      "volume_24h": 4.54,
      "volume_6h": 4.54,
      "volume_1h": 4.54,
      "volume_5m": 0.0,
      "liquidity_usd": 4263.04,
      "market_cap": 2561.0,
      "holder_count": 0,
      "holders_source": "rpc",
      "socials": {
        "twitter": "https://x.com/i/communities/2037838354025222210",
        "telegram": null,
        "website": null
      },
      "pair_created_at": 1774613471000,
      "age_hours": 1972,
      "age_days": 82.2,
      "timestamp": "2026-06-17T16:12:12.916021",
      "source": "dexscreener",
      "vol_acceleration": 1.0,
      "vol_status": "NORMAL"
    },
    {
      "symbol": "Deadwhale",
      "name": "Deadwhale",
      "address": "91E4cACQcnWDf7wYmwwM81HjLvCe6FR6vDT518ospump",
      "chain": "SOL",
      "status": "active",
      "price_usd": 4.879e-06,
      "price_change_1h": 0.0,
      "price_change_6h": -1.72,
      "price_change_24h": -1.72,
      "volume_24h": 5.1,
      "volume_6h": 0.01,
      "volume_1h": 0.0,
      "volume_5m": 0.0,
      "liquidity_usd": 6613.36,
      "market_cap": 4878.0,
      "holder_count": 8570,
      "holders_source": "rpc",
      "socials": {
        "twitter": "https://x.com/i/communities/2037268358526095583",
        "telegram": null,
        "website": "https://deadwhalememe.com/"
      },
      "pair_created_at": 1774560112000,
      "age_hours": 1986,
      "age_days": 82.8,
      "timestamp": "2026-06-17T16:12:18.979288",
      "source": "dexscreener",
      "vol_acceleration": 1.0,
      "vol_status": "NORMAL"
    },
    {
      "symbol": "CAPYBARA",
      "name": "Mythos",
      "address": "Csdoc8vo3ryZ9tSiXxWYsZRTKCMmywG5pR8SC47Hab6B",
      "chain": "SOL",
      "status": "active",
      "price_usd": 7.603e-06,
      "price_change_1h": 0.0,
      "price_change_6h": -1.21,
      "price_change_24h": -12.97,
      "volume_24h": 344.1,
      "volume_6h": 38.37,
      "volume_1h": 0.0,
      "volume_5m": 0.0,
      "liquidity_usd": 7144.64,
      "market_cap": 5544.0,
      "holder_count": 0,
      "holders_source": "rpc",
      "socials": {
        "twitter": "https://x.com/i/communities/2037453944201388141",
        "telegram": null,
        "website": null
      },
      "pair_created_at": 1774578902000,
      "age_hours": 1981,
      "age_days": 82.5,
      "timestamp": "2026-06-17T16:12:25.079133",
      "source": "dexscreener",
      "vol_acceleration": 1.0,
      "vol_status": "NORMAL"
    },
    {
      "symbol": "dapang",
      "name": "D\u00e0 P\u00e0ng",
      "address": "CpP36fvZmbcDUH9tQihQZTcvH2ApwRzHh2pPojyWpump",
      "chain": "SOL",
      "status": "active",
      "price_usd": 2.945e-06,
      "price_change_1h": 0.0,
      "price_change_6h": 0.0,
      "price_change_24h": 0.0,
      "volume_24h": 2.07,
      "volume_6h": 2.07,
      "volume_1h": 0.0,
      "volume_5m": 0.0,
      "liquidity_usd": 4826.77,
      "market_cap": 2933.0,
      "holder_count": 5132,
      "holders_source": "rpc",
      "socials": {
        "twitter": "https://x.com/MariusDima39211",
        "telegram": "https://t.me/DaPangOfficialCTO",
        "website": "https://dapangsolana.com/"
      },
      "pair_created_at": 1774293830000,
      "age_hours": 2060,
      "age_days": 85.8,
      "timestamp": "2026-06-17T16:12:37.286862",
      "source": "dexscreener",
      "vol_acceleration": 1.0,
      "vol_status": "NORMAL"
    },
    {
      "symbol": "PUNCH",
      "name": "\u30d1\u30f3\u30c1",
      "address": "NV2RYH954cTJ3ckFUpvfqaQXU4ARqqDH3562nFSpump",
      "chain": "SOL",
      "status": "active",
      "price_usd": 0.001267,
      "price_change_1h": -1.08,
      "price_change_6h": -0.59,
      "price_change_24h": -7.6,
      "volume_24h": 35477.44,
      "volume_6h": 11118.54,
      "volume_1h": 3647.38,
      "volume_5m": 0.0,
      "liquidity_usd": 233370.06,
      "market_cap": 1266938.0,
      "holder_count": 0,
      "holders_source": "rpc",
      "socials": {
        "twitter": "https://x.com/punch_on_sol?s=21&t=ruzx1xkKsZ3vDPRkeDVwPg",
        "telegram": "https://t.me/punchverif",
        "website": "http://www.punchonsolana.live/"
      },
      "pair_created_at": 1770282065000,
      "age_hours": 3175,
      "age_days": 132.3,
      "timestamp": "2026-06-17T16:12:43.355776",
      "source": "dexscreener",
      "vol_acceleration": 1.0,
      "vol_status": "NORMAL"
    },
    {
      "symbol": "Jellybean",
      "name": "Jellybean",
      "address": "412zDygnwP9DzitnQVgRKUFFTDmrYScFch6P2k39pump",
      "chain": "SOL",
      "status": "active",
      "price_usd": 0.0001063,
      "price_change_1h": 1.56,
      "price_change_6h": 0.11,
      "price_change_24h": -3.71,
      "volume_24h": 3642.91,
      "volume_6h": 1116.03,
      "volume_1h": 40.79,
      "volume_5m": 0.0,
      "liquidity_usd": 47220.65,
      "market_cap": 105872.0,
      "holder_count": 0,
      "holders_source": "rpc",
      "socials": {
        "twitter": "https://x.com/jellybeanonsol?s=21",
        "telegram": "https://t.me/jellybeanog",
        "website": "https://thejellybean.fun"
      },
      "pair_created_at": 1770832014000,
      "age_hours": 3022,
      "age_days": 125.9,
      "timestamp": "2026-06-17T16:12:49.502463",
      "source": "dexscreener",
      "vol_acceleration": 1.0,
      "vol_status": "NORMAL"
    },
    {
      "symbol": "HODL",
      "name": "HODL",
      "address": "Hh3oTaqDCKKfdBgsQEvxp9sUwyNf8x9qmKqEMLBWpump",
      "chain": "SOL",
      "status": "active",
      "price_usd": 0.001943,
      "price_change_1h": 0.89,
      "price_change_6h": 4.91,
      "price_change_24h": -0.15,
      "volume_24h": 51784.39,
      "volume_6h": 8779.45,
      "volume_1h": 2509.18,
      "volume_5m": 36.29,
      "liquidity_usd": 185476.35,
      "market_cap": 1943646.0,
      "holder_count": 0,
      "holders_source": "rpc",
      "socials": {
        "twitter": "https://x.com/hodl2013",
        "telegram": "http://t.me/hodl_2013",
        "website": "https://hodl2013.com"
      },
      "pair_created_at": 1770925712000,
      "age_hours": 2996,
      "age_days": 124.8,
      "timestamp": "2026-06-17T16:12:55.609639",
      "source": "dexscreener",
      "vol_acceleration": 1.0,
      "vol_status": "NORMAL"
    },
    {
      "symbol": "JUICE",
      "name": "JUICE",
      "address": "2LzLh5pHg3nDQz6goTLAvDXfDbSBgAR8qem3bdXdpump",
      "chain": "SOL",
      "status": "active",
      "price_usd": 2.384e-05,
      "price_change_1h": 1.48,
      "price_change_6h": 30.61,
      "price_change_24h": 26.85,
      "volume_24h": 1233.2,
      "volume_6h": 1167.12,
      "volume_1h": 21.99,
      "volume_5m": 0.0,
      "liquidity_usd": 16848.18,
      "market_cap": 22812.0,
      "holder_count": 0,
      "holders_source": "rpc",
      "socials": {
        "twitter": "https://x.com/JuiceLaunch",
        "telegram": null,
        "website": "https://www.juiceeverything.com/"
      },
      "pair_created_at": 1766441506000,
      "age_hours": 4242,
      "age_days": 176.8,
      "timestamp": "2026-06-17T16:13:01.711165",
      "source": "dexscreener",
      "vol_acceleration": 1.0,
      "vol_status": "NORMAL"
    },
    {
      "symbol": "PIZZA",
      "name": "Bitcoin Pizza",
      "address": "G9ivB7K41a4G8m1k4QdxxN4L5eGKL7Mr12S26B85pump",
      "chain": "SOL",
      "status": "active",
      "price_usd": 6.815e-05,
      "price_change_1h": 4.03,
      "price_change_6h": 1.91,
      "price_change_24h": -0.5,
      "volume_24h": 2077.15,
      "volume_6h": 233.85,
      "volume_1h": 37.24,
      "volume_5m": 22.79,
      "liquidity_usd": 29033.15,
      "market_cap": 66779.0,
      "holder_count": 0,
      "holders_source": "rpc",
      "socials": {
        "twitter": "https://x.com/i/communities/2028693567879729365",
        "telegram": null,
        "website": "https://btcpizza2010.com"
      },
      "pair_created_at": 1772520410000,
      "age_hours": 2553,
      "age_days": 106.4,
      "timestamp": "2026-06-17T16:13:07.778216",
      "source": "dexscreener",
      "vol_acceleration": 1.0,
      "vol_status": "NORMAL"
    },
    {
      "symbol": "Momo-chan",
      "name": "\u30e2\u30e2\u3061\u3083\u3093",
      "address": "3zomtMhRRsBpLZeJLS86fgueXE7xAhoN8dnymNh8pump",
      "chain": "SOL",
      "status": "active",
      "price_usd": 5.076e-06,
      "price_change_1h": 0.0,
      "price_change_6h": 0.14,
      "price_change_24h": -1.74,
      "volume_24h": 49.19,
      "volume_6h": 32.87,
      "volume_1h": 0.0,
      "volume_5m": 0.0,
      "liquidity_usd": 6897.8,
      "market_cap": 5075.0,
      "holder_count": 0,
      "holders_source": "rpc",
      "socials": {
        "twitter": "https://x.com/i/communities/2033773408174150024",
        "telegram": null,
        "website": "https://momochanonsol.com/"
      },
      "pair_created_at": 1773667317000,
      "age_hours": 2234,
      "age_days": 93.1,
      "timestamp": "2026-06-17T16:13:13.873688",
      "source": "dexscreener",
      "vol_acceleration": 1.0,
      "vol_status": "NORMAL"
    },
    {
      "symbol": "MAX",
      "name": "maxxing",
      "address": "32CdQdBUxbCsLy5AUHWmyidfwhgGUr9N573NBUrDpump",
      "chain": "SOL",
      "status": "active",
      "price_usd": 0.001131,
      "price_change_1h": 2.74,
      "price_change_6h": -1.0,
      "price_change_24h": -9.22,
      "volume_24h": 155547.14,
      "volume_6h": 13567.03,
      "volume_1h": 2531.52,
      "volume_5m": 46.43,
      "liquidity_usd": 163282.06,
      "market_cap": 1130951.0,
      "holder_count": 0,
      "holders_source": "rpc",
      "socials": {
        "twitter": "https://x.com/_maxxing",
        "telegram": "https://t.me/maxxingTG",
        "website": "https://www.solmaxxing.xyz"
      },
      "pair_created_at": 1764628666000,
      "age_hours": 4745,
      "age_days": 197.7,
      "timestamp": "2026-06-17T16:13:19.940220",
      "source": "dexscreener",
      "vol_acceleration": 1.0,
      "vol_status": "NORMAL"
    },
    {
      "symbol": "testicle",
      "name": "testicle",
      "address": "4TyZGqRLG3VcHTGMcLBoPUmqYitMVojXinAmkL8xpump",
      "chain": "SOL",
      "status": "active",
      "price_usd": 18.065,
      "price_change_1h": 0.0,
      "price_change_6h": 0.0,
      "price_change_24h": 1019598.0,
      "volume_24h": 64788.78,
      "volume_6h": 0.0,
      "volume_1h": 0.0,
      "volume_5m": 0.0,
      "liquidity_usd": 4649419.29,
      "market_cap": 18065856012.0,
      "holder_count": 0,
      "holders_source": "rpc",
      "socials": {
        "twitter": "https://x.com/MerlinDuckCoin",
        "telegram": null,
        "website": "https://merlintheduck.com"
      },
      "pair_created_at": 1781645811000,
      "age_hours": 18,
      "age_days": 0.8,
      "timestamp": "2026-06-17T16:13:26.033112",
      "source": "dexscreener",
      "vol_acceleration": 1.0,
      "vol_status": "NORMAL"
    },
    {
      "symbol": "NOTHING",
      "name": "You'll own nothing & be happy",
      "address": "F7pB3ZdfBnyFw2LRHydWEn9BmhEa5XihXLjhySFRpump",
      "chain": "SOL",
      "status": "active",
      "price_usd": 0.0005868,
      "price_change_1h": 0.7,
      "price_change_6h": -0.23,
      "price_change_24h": -3.63,
      "volume_24h": 20499.69,
      "volume_6h": 2547.27,
      "volume_1h": 36.33,
      "volume_5m": 0.0,
      "liquidity_usd": 115847.45,
      "market_cap": 586828.0,
      "holder_count": 0,
      "holders_source": "rpc",
      "socials": {
        "twitter": "https://x.com/youllownnothing",
        "telegram": "https://t.me/YouWillOwnNothing",
        "website": "https://www.ownnothing.xyz/"
      },
      "pair_created_at": 1762893903000,
      "age_hours": 5227,
      "age_days": 217.8,
      "timestamp": "2026-06-17T16:13:32.103561",
      "source": "dexscreener",
      "vol_acceleration": 1.0,
      "vol_status": "NORMAL"
    },
    {
      "symbol": "Artemis II",
      "name": "Artemis Moon Mission",
      "address": "EJzqpRPxgZZVoVVuCXuQBNXp7mQzeH6FENMfuLRbpump",
      "chain": "SOL",
      "status": "active",
      "price_usd": 2.707e-06,
      "price_change_1h": 0.0,
      "price_change_6h": 0.0,
      "price_change_24h": 0.0,
      "volume_24h": 31.45,
      "volume_6h": 0.0,
      "volume_1h": 0.0,
      "volume_5m": 0.0,
      "liquidity_usd": 4332.06,
      "market_cap": 2704.0,
      "holder_count": 0,
      "holders_source": "rpc",
      "socials": {
        "twitter": "https://x.com/Artemis2coin_",
        "telegram": "https://t.me/artemis2mission",
        "website": "https://www.artemis2coin.fun/"
      },
      "pair_created_at": 1769348704000,
      "age_hours": 3434,
      "age_days": 143.1,
      "timestamp": "2026-06-17T16:13:38.186784",
      "source": "dexscreener",
      "vol_acceleration": 1.0,
      "vol_status": "NORMAL"
    },
    {
      "symbol": "Buttcoin",
      "name": "Buttcoin",
      "address": "Cm6fNnMk7NfzStP9CZpsQA2v3jjzbcYGAxdJySmHpump",
      "chain": "SOL",
      "status": "active",
      "price_usd": 98.73,
      "price_change_1h": 482283.0,
      "price_change_6h": 504267.0,
      "price_change_24h": 495023.0,
      "volume_24h": 553056.02,
      "volume_6h": 118666.86,
      "volume_1h": 118476.96,
      "volume_5m": 0.0,
      "liquidity_usd": 7498033.75,
      "market_cap": 98737949620.0,
      "holder_count": 0,
      "holders_source": "rpc",
      "socials": {
        "twitter": "https://x.com/buttcoin",
        "telegram": "https://t.me/buttcoinonpf",
        "website": "https://www.buttcoin.money"
      },
      "pair_created_at": 1780782542000,
      "age_hours": 258,
      "age_days": 10.8,
      "timestamp": "2026-06-17T16:13:44.224348",
      "source": "dexscreener",
      "vol_acceleration": 1.0,
      "vol_status": "NORMAL"
    },
    {
      "symbol": "Optimistic",
      "name": "Optimistic Minion",
      "address": "2pjcq9k2X5oSArNKiVeQ2ENB63eJt8pwCabciGQGpump",
      "chain": "SOL",
      "status": "active",
      "price_usd": 3.408e-05,
      "price_change_1h": 3.4,
      "price_change_6h": 2.78,
      "price_change_24h": 0.47,
      "volume_24h": 840.57,
      "volume_6h": 184.29,
      "volume_1h": 138.68,
      "volume_5m": 0.0,
      "liquidity_usd": 20681.07,
      "market_cap": 34055.0,
      "holder_count": 0,
      "holders_source": "rpc",
      "socials": {
        "twitter": "https://x.com/i/communities/2034488672767086881",
        "telegram": null,
        "website": "https://www.optimisticonsol.com/"
      },
      "pair_created_at": 1773896929000,
      "age_hours": 2171,
      "age_days": 90.5,
      "timestamp": "2026-06-17T16:13:50.302451",
      "source": "dexscreener",
      "vol_acceleration": 1.0,
      "vol_status": "NORMAL"
    },
    {
      "symbol": "TripleT",
      "name": "Tung Tung Tung Sahur",
      "address": "J8PSdNP3QewKq2Z1JJJFDMaqF7KcaiJhR7gbr5KZpump",
      "chain": "SOL",
      "status": "active",
      "price_usd": 0.006188,
      "price_change_1h": -1.63,
      "price_change_6h": -1.13,
      "price_change_24h": -11.26,
      "volume_24h": 249939.72,
      "volume_6h": 36812.97,
      "volume_1h": 7495.91,
      "volume_5m": 311.4,
      "liquidity_usd": 364422.07,
      "market_cap": 6188294.0,
      "holder_count": 0,
      "holders_source": "rpc",
      "socials": {
        "twitter": "https://x.com/TripleTsol",
        "telegram": "https://t.me/TripleTCommunity",
        "website": null
      },
      "pair_created_at": 1771922626000,
      "age_hours": 2719,
      "age_days": 113.3,
      "timestamp": "2026-06-17T16:13:56.343729",
      "source": "dexscreener",
      "vol_acceleration": 1.0,
      "vol_status": "NORMAL"
    },
    {
      "symbol": "Rosie",
      "name": "Rosie",
      "address": "9QSjVAg5rDfBZPhvKwZcB63St3r6bqohP3Adurkjpump",
      "chain": "SOL",
      "status": "active",
      "price_usd": 4.541e-05,
      "price_change_1h": 0.97,
      "price_change_6h": -8.79,
      "price_change_24h": -17.77,
      "volume_24h": 8058.75,
      "volume_6h": 1440.97,
      "volume_1h": 0.72,
      "volume_5m": 0.0,
      "liquidity_usd": 25021.05,
      "market_cap": 45414.0,
      "holder_count": 0,
      "holders_source": "rpc",
      "socials": {
        "twitter": "https://x.com/i/communities/2032561757802344845",
        "telegram": "https://t.me/rosieverification",
        "website": "https://rosie-dog.vercel.app/"
      },
      "pair_created_at": 1773494598000,
      "age_hours": 2282,
      "age_days": 95.1,
      "timestamp": "2026-06-17T16:14:02.414264",
      "source": "dexscreener",
      "vol_acceleration": 1.0,
      "vol_status": "NORMAL"
    },
    {
      "symbol": "Lobstar",
      "name": "Lobstar",
      "address": "AVF9F4C4j8b1Kh4BmNHqybDaHgnZpJ7W7yLvL7hUpump",
      "chain": "SOL",
      "status": "active",
      "price_usd": 0.0003902,
      "price_change_1h": 0.77,
      "price_change_6h": -3.38,
      "price_change_24h": 1.27,
      "volume_24h": 40588.82,
      "volume_6h": 13992.99,
      "volume_1h": 5071.68,
      "volume_5m": 0.0,
      "liquidity_usd": 112628.41,
      "market_cap": 390201.0,
      "holder_count": 0,
      "holders_source": "rpc",
      "socials": {
        "twitter": "https://x.com/i/communities/2024708338324299795",
        "telegram": null,
        "website": null
      },
      "pair_created_at": 1771561393000,
      "age_hours": 2819,
      "age_days": 117.5,
      "timestamp": "2026-06-17T16:14:08.456127",
      "source": "dexscreener",
      "vol_acceleration": 1.0,
      "vol_status": "NORMAL"
    },
    {
      "symbol": "snowball",
      "name": "snowball",
      "address": "Gbu7JAKhTVtGyRryg8cYPiKNhonXpUqbrZuCDjfUpump",
      "chain": "SOL",
      "status": "active",
      "price_usd": 0.0001851,
      "price_change_1h": -0.15,
      "price_change_6h": -2.1,
      "price_change_24h": -3.45,
      "volume_24h": 5931.4,
      "volume_6h": 1555.3,
      "volume_1h": 524.0,
      "volume_5m": 171.72,
      "liquidity_usd": 75020.6,
      "market_cap": 176156.0,
      "holder_count": 0,
      "holders_source": "rpc",
      "socials": {
        "twitter": "https://x.com/i/communities/2001678386968564186",
        "telegram": "http://t.me/snowballctoportal",
        "website": "https://sb.fun"
      },
      "pair_created_at": 1766080714000,
      "age_hours": 4342,
      "age_days": 180.9,
      "timestamp": "2026-06-17T16:14:14.524642",
      "source": "dexscreener",
      "vol_acceleration": 1.0,
      "vol_status": "NORMAL"
    },
    {
      "symbol": "VIBECOIN",
      "name": "Vibing Cat Coin",
      "address": "AZbem4s8iLJE5eniDZJ7c8q1ahbfMwWgCA8TxVW2tDUB",
      "chain": "SOL",
      "status": "active",
      "price_usd": 0.001047,
      "price_change_1h": 0.6,
      "price_change_6h": -1.53,
      "price_change_24h": -8.89,
      "volume_24h": 4128.11,
      "volume_6h": 1594.72,
      "volume_1h": 250.53,
      "volume_5m": 0.0,
      "liquidity_usd": 75937.16,
      "market_cap": 1047069.0,
      "holder_count": 0,
      "holders_source": "rpc",
      "socials": {
        "twitter": "https://x.com/vibecoinonanon?s=21",
        "telegram": "https://t.me/VIBECOINCAT",
        "website": "https://anoncoin.it/vibecoin"
      },
      "pair_created_at": 1755441758000,
      "age_hours": 7297,
      "age_days": 304.0,
      "timestamp": "2026-06-17T16:14:20.589097",
      "source": "dexscreener",
      "vol_acceleration": 1.0,
      "vol_status": "NORMAL"
    },
    {
      "symbol": "GOYIM",
      "name": "Goyim",
      "address": "9S8edqWxoWz5LYLnxWUmWBJnePg35WfdYQp7HQkUpump",
      "chain": "SOL",
      "status": "active",
      "price_usd": 7.311e-05,
      "price_change_1h": -0.66,
      "price_change_6h": -1.18,
      "price_change_24h": -0.57,
      "volume_24h": 1000.05,
      "volume_6h": 0.86,
      "volume_1h": 0.0,
      "volume_5m": 0.0,
      "liquidity_usd": 41261.61,
      "market_cap": 73113.0,
      "holder_count": 0,
      "holders_source": "rpc",
      "socials": {
        "twitter": "https://x.com/GoyimFanAcc",
        "telegram": "https://t.me/goyimtoke",
        "website": "https://goyimtoken.com/"
      },
      "pair_created_at": 1769958443000,
      "age_hours": 3265,
      "age_days": 136.0,
      "timestamp": "2026-06-17T16:14:26.657909",
      "source": "dexscreener",
      "vol_acceleration": 1.0,
      "vol_status": "NORMAL"
    },
    {
      "symbol": "CHIBI",
      "name": "Chibification",
      "address": "2TpMjYXnrgxoeVCq2i6EAR8vNWqe5MNvHCz3bENNpump",
      "chain": "SOL",
      "status": "active",
      "price_usd": 0.0001057,
      "price_change_1h": 1.92,
      "price_change_6h": -2.35,
      "price_change_24h": -7.57,
      "volume_24h": 2748.57,
      "volume_6h": 1027.79,
      "volume_1h": 276.88,
      "volume_5m": 20.48,
      "liquidity_usd": 39119.08,
      "market_cap": 105716.0,
      "holder_count": 0,
      "holders_source": "rpc",
      "socials": {
        "twitter": "https://x.com/ChibificDEV",
        "telegram": "https://t.me/chibifii",
        "website": null
      },
      "pair_created_at": 1773913358000,
      "age_hours": 2166,
      "age_days": 90.2,
      "timestamp": "2026-06-17T16:14:32.737185",
      "source": "dexscreener",
      "vol_acceleration": 1.0,
      "vol_status": "NORMAL"
    },
    {
      "symbol": "NOTHING2",
      "name": "Nothing To Lose",
      "address": "7mtXLUoAcT9Sxrf1K5PjSmfkPbYMyMP5pmrdFFixbonk",
      "chain": "SOL",
      "status": "active",
      "price_usd": 5.245e-05,
      "price_change_1h": 0.0,
      "price_change_6h": 0.0,
      "price_change_24h": 0.0,
      "volume_24h": 102.9,
      "volume_6h": 0.0,
      "volume_1h": 0.0,
      "volume_5m": 0.0,
      "liquidity_usd": 76455.06,
      "market_cap": 52452.0,
      "holder_count": 0,
      "holders_source": "rpc",
      "socials": {
        "twitter": "https://x.com/i/communities/2037084621385425092",
        "telegram": "https://t.me/nothing2losesol",
        "website": "https://nothingtolose.lol/"
      },
      "pair_created_at": 1774037046000,
      "age_hours": 2132,
      "age_days": 88.8,
      "timestamp": "2026-06-17T16:14:38.810089",
      "source": "dexscreener",
      "vol_acceleration": 1.0,
      "vol_status": "NORMAL"
    },
    {
      "symbol": "Lockdown",
      "name": "Energy Lockdown",
      "address": "57wDExcxN6hAtYgcXoAXqSxrdCMwY4HNioWNM1Mtpump",
      "chain": "SOL",
      "status": "active",
      "price_usd": 3.232e-06,
      "price_change_1h": 0.0,
      "price_change_6h": -0.74,
      "price_change_24h": -0.74,
      "volume_24h": 16.49,
      "volume_6h": 16.49,
      "volume_1h": 0.0,
      "volume_5m": 0.0,
      "liquidity_usd": 4449.55,
      "market_cap": 3218.0,
      "holder_count": 0,
      "holders_source": "rpc",
      "socials": {
        "twitter": "https://x.com/i/communities/2035616033952731544",
        "telegram": null,
        "website": "https://www.x.com/search?q=energy%20lockdown&src=typed_query"
      },
      "pair_created_at": 1774165370000,
      "age_hours": 2096,
      "age_days": 87.3,
      "timestamp": "2026-06-17T16:14:44.898236",
      "source": "dexscreener",
      "vol_acceleration": 1.0,
      "vol_status": "NORMAL"
    },
    {
      "symbol": "TERAFAB",
      "name": "Terafab",
      "address": "EncFm8nRh1VBwcRmGugTUzoGsC1n2srWesKDkiMAYWLt",
      "chain": "SOL",
      "status": "active",
      "price_usd": 5.825e-05,
      "price_change_1h": 1.88,
      "price_change_6h": 2.41,
      "price_change_24h": 8.52,
      "volume_24h": 7492.99,
      "volume_6h": 664.62,
      "volume_1h": 6.86,
      "volume_5m": 0.0,
      "liquidity_usd": 26227.88,
      "market_cap": 58246.0,
      "holder_count": 0,
      "holders_source": "rpc",
      "socials": {
        "twitter": "https://x.com/i/communities/2032819528636272922",
        "telegram": null,
        "website": "https://terafab.ceo/"
      },
      "pair_created_at": 1773495773000,
      "age_hours": 2282,
      "age_days": 95.1,
      "timestamp": "2026-06-17T16:14:50.988567",
      "source": "dexscreener",
      "vol_acceleration": 1.0,
      "vol_status": "NORMAL"
    },
    {
      "symbol": "Lost",
      "name": "Pumpfun ruined my life",
      "address": "n3ShrNZRCoMrw5Gww7rPMxVbDq3to3YwsGkDz19pump",
      "chain": "SOL",
      "status": "active",
      "price_usd": 6.743e-06,
      "price_change_1h": 0.0,
      "price_change_6h": 0.51,
      "price_change_24h": 2.16,
      "volume_24h": 289.02,
      "volume_6h": 112.15,
      "volume_1h": 0.0,
      "volume_5m": 0.0,
      "liquidity_usd": 7941.04,
      "market_cap": 6741.0,
      "holder_count": 0,
      "holders_source": "rpc",
      "socials": {
        "twitter": "https://x.com/lostonpumpfun?s=21",
        "telegram": null,
        "website": "https://lostonpump.fun/"
      },
      "pair_created_at": 1774199898000,
      "age_hours": 2086,
      "age_days": 86.9,
      "timestamp": "2026-06-17T16:15:03.330632",
      "source": "dexscreener",
      "vol_acceleration": 1.0,
      "vol_status": "NORMAL"
    },
    {
      "symbol": "7",
      "name": "The 7 Wanderers",
      "address": "84cAEWqiDsV5xXh6CB69Hi3HcnumBbdjH4THfyorpump",
      "chain": "SOL",
      "status": "active",
      "price_usd": 7.051e-06,
      "price_change_1h": 0.0,
      "price_change_6h": -2.79,
      "price_change_24h": -1.84,
      "volume_24h": 28.37,
      "volume_6h": 20.07,
      "volume_1h": 0.0,
      "volume_5m": 0.0,
      "liquidity_usd": 8578.84,
      "market_cap": 7048.0,
      "holder_count": 0,
      "holders_source": "rpc",
      "socials": {
        "twitter": "https://x.com/i/communities/2036098188285763894",
        "telegram": null,
        "website": "https://the7wanderers.com/"
      },
      "pair_created_at": 1774277677000,
      "age_hours": 2065,
      "age_days": 86.0,
      "timestamp": "2026-06-17T16:15:09.394540",
      "source": "dexscreener",
      "vol_acceleration": 1.0,
      "vol_status": "NORMAL"
    }
  ]
}